{
  "generated_at_utc": "2026-03-16T09:45:37.010903+00:00",
  "interval": "1h",
  "historical": [
    {
      "symbol": "INFY.NS",
      "interval": "1h",
      "dataset_type": "historical",
      "exchange": "NSE",
      "asset_type": "equity",
      "status": "train_ready",
      "train_ready": true,
      "first_timestamp": "2025-03-17T03:45:00+00:00",
      "last_timestamp": "2026-03-16T08:45:00+00:00",
      "row_count": 1835,
      "duplicate_count": 0,
      "expected_rows": 1819,
      "missing_intervals": 0,
      "gap_count": 246,
      "largest_gap_intervals": 89,
      "zero_volume_ratio": 0.114986,
      "coverage_pct": 100.0,
      "history_days": 365,
      "source_name": "nsemine,yfinance",
      "source_type": "official_api",
      "details_json": {
        "quality_flags": []
      },
      "updated_at": "2026-03-16T09:44:49.123010+00:00"
    },
    {
      "symbol": "RELIANCE.NS",
      "interval": "1h",
      "dataset_type": "historical",
      "exchange": "NSE",
      "asset_type": "equity",
      "status": "train_ready",
      "train_ready": true,
      "first_timestamp": "2025-03-17T03:45:00+00:00",
      "last_timestamp": "2026-03-16T08:45:00+00:00",
      "row_count": 1834,
      "duplicate_count": 0,
      "expected_rows": 1819,
      "missing_intervals": 0,
      "gap_count": 245,
      "largest_gap_intervals": 89,
      "zero_volume_ratio": 0.111778,
      "coverage_pct": 100.0,
      "history_days": 365,
      "source_name": "nsemine,yfinance",
      "source_type": "official_api",
      "details_json": {
        "quality_flags": []
      },
      "updated_at": "2026-03-16T09:44:45.328135+00:00"
    },
    {
      "symbol": "TATASTEEL.NS",
      "interval": "1h",
      "dataset_type": "historical",
      "exchange": "NSE",
      "asset_type": "equity",
      "status": "train_ready",
      "train_ready": true,
      "first_timestamp": "2025-03-17T03:45:00+00:00",
      "last_timestamp": "2026-03-16T08:45:00+00:00",
      "row_count": 1833,
      "duplicate_count": 0,
      "expected_rows": 1819,
      "missing_intervals": 0,
      "gap_count": 245,
      "largest_gap_intervals": 89,
      "zero_volume_ratio": 0.113475,
      "coverage_pct": 100.0,
      "history_days": 365,
      "source_name": "nsemine,yfinance",
      "source_type": "official_api",
      "details_json": {
        "quality_flags": []
      },
      "updated_at": "2026-03-16T09:44:45.290050+00:00"
    },
    {
      "symbol": "TCS.NS",
      "interval": "1h",
      "dataset_type": "historical",
      "exchange": "NSE",
      "asset_type": "equity",
      "status": "train_ready",
      "train_ready": true,
      "first_timestamp": "2025-03-17T03:45:00+00:00",
      "last_timestamp": "2026-03-16T08:45:00+00:00",
      "row_count": 1833,
      "duplicate_count": 0,
      "expected_rows": 1819,
      "missing_intervals": 0,
      "gap_count": 247,
      "largest_gap_intervals": 89,
      "zero_volume_ratio": 0.114566,
      "coverage_pct": 100.0,
      "history_days": 365,
      "source_name": "nsemine,yfinance",
      "source_type": "official_api",
      "details_json": {
        "quality_flags": []
      },
      "updated_at": "2026-03-16T09:44:48.960891+00:00"
    }
  ],
  "live": [
    {
      "symbol": "RELIANCE.NS",
      "interval": "1h",
      "dataset_type": "live",
      "exchange": "NSE",
      "asset_type": "equity",
      "status": "fresh",
      "train_ready": true,
      "first_timestamp": "NaT",
      "last_timestamp": "2026-03-16T09:45:23.229281+00:00",
      "row_count": 1,
      "duplicate_count": 0,
      "expected_rows": null,
      "missing_intervals": null,
      "gap_count": null,
      "largest_gap_intervals": null,
      "zero_volume_ratio": null,
      "coverage_pct": null,
      "history_days": null,
      "source_name": "nsepython",
      "source_type": "fallback_scraper",
      "details_json": {
        "freshness_status": "fresh",
        "is_final_bar": false,
        "observation_kind": "quote",
        "source_error": null,
        "source_status": "ok",
        "staleness_seconds": 0.267091
      },
      "updated_at": "2026-03-16T09:45:23.496423+00:00"
    },
    {
      "symbol": "TATASTEEL.NS",
      "interval": "1h",
      "dataset_type": "live",
      "exchange": "NSE",
      "asset_type": "equity",
      "status": "fresh",
      "train_ready": true,
      "first_timestamp": "NaT",
      "last_timestamp": "2026-03-16T09:45:23.917208+00:00",
      "row_count": 1,
      "duplicate_count": 0,
      "expected_rows": null,
      "missing_intervals": null,
      "gap_count": null,
      "largest_gap_intervals": null,
      "zero_volume_ratio": null,
      "coverage_pct": null,
      "history_days": null,
      "source_name": "nsepython",
      "source_type": "fallback_scraper",
      "details_json": {
        "freshness_status": "fresh",
        "is_final_bar": false,
        "observation_kind": "quote",
        "source_error": null,
        "source_status": "ok",
        "staleness_seconds": 0.064022
      },
      "updated_at": "2026-03-16T09:45:23.981297+00:00"
    }
  ],
  "summary": {
    "historical_train_ready": 4,
    "historical_partial": 0,
    "historical_failed": 0,
    "live_fresh": 2,
    "live_stale": 0,
    "live_failed": 0
  }
}