{
  "timestamp_utc": "2026-03-19T15:26:35.907520+00:00",
  "run_dir": "data/reports/training_runs_smoke/regime_aware_1h_20260319_152632",
  "symbols_requested": [
    "TATASTEEL.NS",
    "RELIANCE.NS",
    "USDINR=X"
  ],
  "symbols_succeeded": [],
  "symbols_skipped": [
    {
      "symbol": "USDINR=X",
      "reason": "forex_context_only",
      "details": "Configured via --fx-context-symbol=USDINR=X"
    }
  ],
  "symbols_failed": [
    {
      "symbol": "TATASTEEL.NS",
      "error": "TATASTEEL.NS only has 71 rows after preprocessing. Check ffill and feature engineering nulls."
    },
    {
      "symbol": "RELIANCE.NS",
      "error": "Only 79 rows available for RELIANCE.NS; need at least 300."
    }
  ],
  "config": {
    "symbols": [
      "TATASTEEL.NS",
      "RELIANCE.NS",
      "USDINR=X"
    ],
    "data_path": null,
    "database_url": null,
    "gold_dir": "data/gold",
    "interval": "1h",
    "limit": 2500,
    "output_root": "data/reports/training_runs_smoke",
    "seed": 42,
    "device": "cpu",
    "epochs": 2,
    "batch_size": 64,
    "patience": 2,
    "scheduler_patience": 1,
    "lr": 0.001,
    "weight_decay": 0.0001,
    "dropout": 0.25,
    "reg_window": 20,
    "cnn_window": 30,
    "neutral_threshold": 0.0045,
    "arima_order": "5,1,0",
    "lstm_hidden_size": 64,
    "lstm_layers": 2,
    "min_rows": 300,
    "fx_context_symbol": "USDINR=X"
  },
  "summaries": []
}